{"type": "Feature", "id": 12514066, "geometry": {"type": "Point", "coordinates": [37.5881, 0.3436]}, "properties": {"woe:id": 12514066, "woe:parent_id": 1527329, "woe:name": "Isiolo Airport", "woe:placetype": 14, "woe:placetype_name": "Airport", "woe:lang": "ENG", "iso:country": "KE", "meta:provider": ["geoplanet:7.3.1", "geoplanet:7.3.2", "geoplanet:7.4.0", "geoplanet:7.4.1", "geoplanet:7.5.1", "geoplanet:7.5.2", "geoplanet:7.6.0", "geoplanet:7.8.1", "geoplanet:7.9.0", "geoplanet:7.10.0", "geoplanet:8.0.0", "woeplanet:8.0.0"], "meta:indexed": "2020-08-20T20:27:00.163183", "meta:updated": "2020-10-14T11:17:25.482275", "woe:hierarchy": {"continent": 24865670, "country": 23424863, "town": 0, "planet": 1, "county": 0, "suburb": 0, "state": 2345939, "region": 0, "localadmin": 0}, "woe:timezone_id": 28350721, "woe:hash": "sb49zqdcd5wv", "woe:centroid": [37.5881, 0.3436], "geom:latitude": 0.3436, "geom:longitude": 37.5881, "geom:hash": "sb49zqdcd5wv", "woe:latitude": 0.3436, "geom:centroid": [37.5881, 0.3436], "woe:longitude": 37.5881, "woe:repo": "woeplanet-airport-ke", "geom:area": 0.0, "woe:scale": 19}}