{"type": "Feature", "id": 12514067, "geometry": {"type": "Point", "coordinates": [36.922161, -1.31697]}, "properties": {"woe:id": 12514067, "woe:parent_id": 1527049, "woe:name": "Jomo Kenyatta International Airport", "woe:placetype": 14, "woe:placetype_name": "Airport", "woe:lang": "ENG", "iso:country": "KE", "meta:provider": ["geoplanet:7.3.1", "geoplanet:7.3.2", "geoplanet:7.4.0", "geoplanet:7.4.1", "geoplanet:7.5.1", "geoplanet:7.5.2", "geoplanet:7.6.0", "geoplanet:7.8.1", "geoplanet:7.9.0", "geoplanet:7.10.0", "geoplanet:8.0.0", "woeplanet:8.0.0"], "meta:indexed": "2020-08-20T20:27:00.164014", "woe:alias_ENG_V": ["Jomo Kenyatta", "Jomo Kenyatta Airport", "Jomo Kenyatta International", "NBO Airport", "NBO"], "meta:updated": "2020-10-14T11:17:25.481588", "woe:hierarchy": {"continent": 24865670, "country": 23424863, "town": 0, "planet": 1, "county": 0, "suburb": 0, "state": 2345940, "region": 0, "localadmin": 0}, "woe:timezone_id": 28350721, "woe:hash": "kzf280mbhdyx", "woe:centroid": [36.922161, -1.31697], "geom:latitude": -1.31697, "geom:longitude": 36.922161, "geom:hash": "kzf280mbhdyx", "woe:latitude": -1.31697, "geom:centroid": [36.922161, -1.31697], "woe:longitude": 36.922161, "woe:repo": "woeplanet-airport-ke", "geom:area": 0.0, "woe:scale": 19}}